mqboost/__init__.py
mqboost/base.py
mqboost/constraints.py
mqboost/dataset.py
mqboost/encoder.py
mqboost/objective.py
mqboost/optimize.py
mqboost/regressor.py
mqboost/utils.py
mqboost-0.2.10.dist-info/METADATA
mqboost-0.2.10.dist-info/WHEEL
mqboost-0.2.10.dist-info/RECORD
