Metadata-Version: 2.1
Name: mqboost
Version: 0.2.10
Summary: Monotonic composite quantile gradient boost regressor
Home-page: https://github.com/RektPunk/MQBoost
Author: RektPunk
Author-email: rektpunk@gmail.com
Requires-Python: >=3.9,<4.0
Classifier: Programming Language :: Python :: 3
Classifier: Programming Language :: Python :: 3.9
Classifier: Programming Language :: Python :: 3.10
Classifier: Programming Language :: Python :: 3.11
Classifier: Programming Language :: Python :: 3.12
Classifier: Programming Language :: Python :: 3.13
Classifier: Topic :: Software Development :: Libraries :: Python Modules
Requires-Dist: lightgbm (>=4.3.0,<5.0.0)
Requires-Dist: numpy (>=2.0.0,<3.0.0)
Requires-Dist: optuna (>=3.6.1,<4.0.0)
Requires-Dist: pandas (>=2.2.2,<3.0.0)
Requires-Dist: scikit-learn (>=1.5.1,<2.0.0)
Requires-Dist: xgboost (>=2.1.0,<3.0.0)
Project-URL: Repository, https://github.com/RektPunk/MQBoost
